sinemarc_api/__init__.py
sinemarc_api/example/__init__.py
sinemarc_api/example/__main__.py
sinemarc_api/example/influxDB_example.py
sinemarc_api/example/postgresDB_example.py
sinemarc_api/lib/__init__.py
sinemarc_api/lib/definitions.py
sinemarc_api/lib/exception_definition.py
sinemarc_api/lib/srcapi_core.py
sinemarc_api-0.0.1.dist-info/LICENSE
sinemarc_api-0.0.1.dist-info/METADATA
sinemarc_api-0.0.1.dist-info/WHEEL
sinemarc_api-0.0.1.dist-info/entry_points.txt
sinemarc_api-0.0.1.dist-info/top_level.txt
sinemarc_api-0.0.1.dist-info/RECORD
