Metadata-Version: 2.1
Name: sinemarc-api
Version: 0.0.1
Summary: A libary for the rest api of SINEMA RC
Home-page: 
Author: SIEMENS Support
Author-email: Torsten Keidel <siemens@support.com>
Project-URL: Homepage, https://github.com/siemens/sinema-rc-tools
Project-URL: Bug Tracker, https://github.com/siemens/sinema-rc-tools/issues
Keywords: network,sinemarc
Classifier: Programming Language :: Python :: 3
Classifier: License :: OSI Approved :: MIT License
Classifier: Operating System :: OS Independent
Requires-Python: >=3.7
License-File: LICENSE
Requires-Dist: requests
